spocu/__init__.py
spocu/spocu_pytorch.py
spocu/spocu_tensorflow.py
spocu-0.0.1.dist-info/LICENSE.md
spocu-0.0.1.dist-info/METADATA
spocu-0.0.1.dist-info/WHEEL
spocu-0.0.1.dist-info/top_level.txt
spocu-0.0.1.dist-info/RECORD
