Metadata-Version: 2.1
Name: spocu
Version: 0.0.1
Summary: Spocu activation function in Pytorch and Tensorflow.
Home-page: https://github.com/pacocp/spocu-pytorch
Author: Francisco Carrillo Pérez
Author-email: carrilloperezfrancisco@protonmail.com
License: UNKNOWN
Project-URL: Bug Tracker, https://github.com/pacocp/spocu-pytorch/issues
Platform: UNKNOWN
Classifier: Programming Language :: Python :: 3
Classifier: License :: OSI Approved :: MIT License
Classifier: Operating System :: OS Independent
Requires-Python: >=3.6
